paralang_cli/__init__.py
paralang_cli/__main__.py
paralang_cli/logging.py
paralang_cli/utils.py
paralang_cli/scripts/__init__.py
paralang_cli/scripts/para.py
paralang_cli/scripts/paraproj.py
paralang_cli-0.1.dev7.dist-info/LICENSE
paralang_cli-0.1.dev7.dist-info/METADATA
paralang_cli-0.1.dev7.dist-info/WHEEL
paralang_cli-0.1.dev7.dist-info/entry_points.txt
paralang_cli-0.1.dev7.dist-info/top_level.txt
paralang_cli-0.1.dev7.dist-info/RECORD
