Metadata-Version: 2.1
Name: paralang-cli
Version: 0.1.dev7
Summary: Command Line Interface Implementation for the Para programming compiler
Home-page: https://github.com/Para-Lang/Para-CLI/
Author: Luna Klatzer
Author-email: luna.klatzer@gmail.com
Maintainer: Luna Klatzer
Maintainer-email: luna.klatzer@gmail.com
License: GNU GENERAL PUBLIC LICENSE v3.0
Project-URL: Issue-Page, https://github.com/Para-Lang/Para-CLI/issues/
Project-URL: Changelog, https://github.com/Para-Lang/Para-CLI/releases
Platform: UNKNOWN
Classifier: Development Status :: 2 - Pre-Alpha
Classifier: Programming Language :: Python :: 3
Classifier: Programming Language :: Python :: 3.8
Classifier: Programming Language :: Python :: 3.9
Classifier: Programming Language :: Python :: 3.10
Classifier: Programming Language :: C
Classifier: License :: OSI Approved :: GNU General Public License v3 (GPLv3)
Classifier: Environment :: Console
Classifier: Intended Audience :: Developers
Classifier: Intended Audience :: Information Technology
Classifier: Operating System :: POSIX
Classifier: Operating System :: MacOS :: MacOS X
Classifier: Operating System :: Microsoft :: Windows
Requires-Python: >=3.8
License-File: LICENSE
Requires-Dist: colorama (>=0.4.4)
Requires-Dist: click (>=8.0.0)
Requires-Dist: rich (>=10.0.0)
Requires-Dist: paralang-base (>=0.1.dev7)
